all_pay/__init__.py
all_pay/compat.py
all_pay/pay.py
all_pay/pay_error.py
all_pay/pay_order.py
all_pay/pay_response.py
all_pay/pay_type.py
all_pay/ali/__init__.py
all_pay/wx/__init__.py
all_pay/wx/utils.py
all_pay-1.0.3.dist-info/METADATA
all_pay-1.0.3.dist-info/WHEEL
all_pay-1.0.3.dist-info/top_level.txt
all_pay-1.0.3.dist-info/RECORD
