Metadata-Version: 2.1
Name: all-pay
Version: 1.0.3
Summary: Python SDK for multi pay ,such as AliPay、WeChatpay
Home-page: https://github.com/adisonhuang/pay-python
Author: adison
Author-email: adison5321@gmail.com
Maintainer: adison
Maintainer-email: adison5321@gmail.com
License: MIT
Keywords: WeChatpay,AliPay,Pay
Platform: UNKNOWN
Classifier: Development Status :: 5 - Production/Stable
Classifier: License :: OSI Approved :: MIT License
Classifier: Operating System :: MacOS
Classifier: Operating System :: POSIX
Classifier: Operating System :: POSIX :: Linux
Classifier: Programming Language :: Python
Classifier: Programming Language :: Python :: 2.7
Classifier: Programming Language :: Python :: 3.5
Classifier: Programming Language :: Python :: 3.6
Classifier: Programming Language :: Python :: 3.7
Classifier: Programming Language :: Python :: Implementation :: CPython
Classifier: Programming Language :: Python :: Implementation :: PyPy
Classifier: Intended Audience :: Developers
Classifier: Topic :: Software Development :: Libraries
Classifier: Topic :: Software Development :: Libraries :: Python Modules
Classifier: Topic :: Utilities
Requires-Dist: requests (==2.21.0)
Requires-Dist: pycryptodome (==3.7.2)
Requires-Dist: xmltodict (==0.11.0)
